Workbook

Sheet 📊 Executive Summary
A1: ESPRESSO YOURSELF & TEA HOUSE — INVENTORY RECONCILIATION AUDIT
A2: Branch: Cebu City (#30) | Audit Date: September 22, 2026 | Beginning Stocks (Aug 8) + Deliveries (Aug 13 - Sept 3) vs Current Physical & POS
A4: TOTAL ITEMS AUDITED | C4: BEGINNING STOCKS (AUG 8) | E4: ADDITIONAL RESTOCKING | G4: CURRENT PHYSICAL VALUE | I4: OUT OF STOCK (URGENT)
A5: 59 Items | C5: ₱16,846.50 | E5: ₱64,960.50 | G5: ₱63,771.18 | I5: 3 Items
A6: Full Store Coverage | C6: Initial Store Delivery | E6: Aug 13, 24, Sept 2 & 3 | G6: Current Store Valuation | I6: Immediate Restock Required
A8: 📊 DEPARTMENT INVENTORY FLOW: BEGINNING STOCKS → ADDITIONAL RESTOCKS → CURRENT VALUE
A9: Category / Department | B9: Items | C9: Beginning Val (₱) | D9: Additional Val (₱) | E9: Total Available (₱) | F9: Current Stock (₱) | G9: Total Consumed (₱) | H9: Matches | I9: Low | J9: OOS | K9: Operational Recommendation
A10: 1. Cups & Packaging Consumables | B10: 3 | C10: ='📋 Complete Inventory Audit'!E9*1 | D10: ='📋 Complete Inventory Audit'!F9*1 | E10: =C10+D10 | F10: ='📋 Complete Inventory Audit'!M9 | G10: =E10-F10 | H10: 0 | I10: 0 | J10: 0 | K10: Healthy stock. All 3 cup sizes sufficient for high drink volume.
A11: 2. Coffee Beans & Specialty Roasts | B11: 2 | C11: ='📋 Complete Inventory Audit'!E13*1 | D11: ='📋 Complete Inventory Audit'!F13*1 | E11: =C11+D11 | F11: ='📋 Complete Inventory Audit'!M13 | G11: =E11-F11 | H11: 1 | I11: 0 | J11: 0 | K11: Australia's Own 100% match. 3kg Concept Blend left (7kg ground).
A12: 3. Torani Flavor Syrups & Purées | B12: 12 | C12: ='📋 Complete Inventory Audit'!E27*1 | D12: ='📋 Complete Inventory Audit'!F27*1 | E12: =C12+D12 | F12: ='📋 Complete Inventory Audit'!M27 | G12: =E12-F12 | H12: 12 | I12: 0 | J12: 0 | K12: All 12 Torani bottles and gallons match POS records exactly.
A13: 4. SHOTT New Zealand Syrups | B13: 7 | C13: ='📋 Complete Inventory Audit'!E36*1 | D13: ='📋 Complete Inventory Audit'!F36*1 | E13: =C13+D13 | F13: ='📋 Complete Inventory Audit'!M36 | G13: =E13-F13 | H13: 3 | I13: 2 | J13: 1 | K13: Pink Guava EMPTY! Mango & Pomegranate low (<250ml). Order restock.
A14: 5. Condiments, Spreads & Mixes | B14: 6 | C14: ='📋 Complete Inventory Audit'!E44*1 | D14: ='📋 Complete Inventory Audit'!F44*1 | E14: =C14+D14 | F14: ='📋 Complete Inventory Audit'!M44 | G14: =E14-F14 | H14: 0 | I14: 0 | J14: 0 | K14: 12+ cans condensed milk, active caramel fudge and Biscoff sauces.
A15: 6. Powders & Brewing Tea Leaves | B15: 7 | C15: ='📋 Complete Inventory Audit'!E53*1 | D15: ='📋 Complete Inventory Audit'!F53*1 | E15: =C15+D15 | F15: ='📋 Complete Inventory Audit'!M53 | G15: =E15-F15 | H15: 3 | I15: 0 | J15: 0 | K15: Jasmine Tea (597g) & Matcha (101g) match. Choco powder has +612g reserve.
A16: 7. Dilmah Specialty Tea Packs | B16: 6 | C16: ='📋 Complete Inventory Audit'!E61*1 | D16: ='📋 Complete Inventory Audit'!F61*1 | E16: =C16+D16 | F16: ='📋 Complete Inventory Audit'!M61 | G16: =E16-F16 | H16: 6 | I16: 0 | J16: 0 | K16: Flawless tracking: Chamomile, Green, Oolong, Jasmine 100/100, Mint 98/98!
A17: 8. Grab-and-Go Retail Snacks | B17: 5 | C17: ='📋 Complete Inventory Audit'!E68*1 | D17: ='📋 Complete Inventory Audit'!F68*1 | E17: =C17+D17 | F17: ='📋 Complete Inventory Audit'!M68 | G17: =E17-F17 | H17: 0 | I17: 3 | J17: 1 | K17: Pringles Sour Cream EMPTY. Cheddar, Original, Cheetos at 3 left!
A18: 9. Retail Drinks, Water & Beers | B18: 11 | C18: ='📋 Complete Inventory Audit'!E81*1 | D18: ='📋 Complete Inventory Audit'!F81*1 | E18: =C18+D18 | F18: ='📋 Complete Inventory Audit'!M81 | G18: =E18-F18 | H18: 3 | I18: 2 | J18: 1 | K18: Nature Spring 500ml EMPTY (54 sold). Nature Spring 1L is 100% match (15pcs)!
A19: TOTAL / STOREWIDE VALUATION: | B19: =SUM(B10:B18) | C19: =SUM(C10:C18) | D19: =SUM(D10:D18) | E19: =SUM(E10:E18) | F19: =SUM(F10:F18) | G19: =SUM(G10:G18) | H19: =SUM(H10:H18) | I19: =SUM(I10:I18) | J19: =SUM(J10:J18) | K19: Urgent restock required for 3 out-of-stock items.
A20: 💡 AUDITOR & BARISTA KEY TAKEAWAYS FOR ESPRESSO YOURSELF & TEA HOUSE
A21: 1. Complete Delivery Traceability | D21: Every single stock movement has been mapped from the official record (Espresso-Beginning Stocks (5).xlsx): Beginning Inventory (Aug 8) + 4 successive replenishment deliveries (Aug 13, Aug 24, Sept 2, Sept 3).
A22: 2. Flawless Alignment on Teas & Syrups | D22: Dilmah Specialty Teas showed an astounding match (100 Chamomile, 98 Peppermint, 100 Green, 100 Oolong, 100 Jasmine Green, 93 Earl Grey). All 12 Torani Syrups and purees match 100% with the POS inventory system.
A23: 3. Perfect Mathematical Match on Nature Spring 1L | D23: Nature Spring 1L started at 20 bottles delivery; the POS recorded exactly 5 customer sales, and the physical count found EXACTLY 15 bottles (20 - 5 = 15). Zero shrinkage!
A24: 4. Critical Out-of-Stock Alert: Nature Spring 500ml | D24: Nature Spring 500ml is completely EMPTY. All 35+ bottles delivered on Aug 24 were sold. Customers will be turned away without water. Urgent reorder of 2-3 cases needed today!
A25: 5. Urgent Snack Reorder (Pringles & Cheetos) | D25: Pringles Sour Cream is EMPTY (all 3 sold). Pringles Cheddar, Original, and Cheetos each have only 3 units remaining. Restock before the weekend.
A26: 6. High Consumption Items | D26: Concept Blend 1 Coffee Beans: 7kg ground from 10kg beginning stock (3kg left). Doreen Condensed Milk: 11.47 cans consumed from 24 cans beginning stock (12.53 cans left). Sugar syrup: 8 bottles used from 11 bottles available (3 bottles left).

Sheet 📋 Complete Inventory Audit
A1: ESPRESSO YOURSELF & TEA HOUSE — COMPREHENSIVE INVENTORY RECONCILIATION
A2: Branch #30 (Cebu City) | Beginning Stocks (Aug 8) + Deliveries (Aug 13 - Sept 3) vs Current Physical & POS Stock | Audit Date: September 22, 2026
A4: SKU / Code | B4: Item Description & Specifications | C4: UOM | D4: Unit Cost (₱) | E4: Beginning Stock (Aug 8) | F4: Additional Stock (Aug 13 - Sept 3) | G4: Total Available Stock | H4: ★ Inventory Now ★ (Physical Count) | I4: Barista Raw Note (Input) | J4: POS System Stock | K4: Variance (Phys - POS) | L4: Total Consumed / Sold | M4: Current Physical Value (₱) | N4: Variance Value (₱) | O4: Audit Status | P4: Flag | Q4: Delivery Source & Operational Remarks
A5: 📦 1. CUPS & PACKAGING CONSUMABLES
A6: PKG-001 | B6: Plastic Cup 16oz (Cold PET) | C6: pcs | D6: 2.8 | E6: 300 | F6: 500 | G6: =E6+F6 | H6: 709 | I6: 709pcs | J6: 300 | K6: =H6-J6 | L6: =G6-H6 | M6: =H6*D6 | N6: =K6*D6 | O6: 🔺 SURPLUS / RESTOCK | P6: 🔵 | Q6: Initial setup 300pcs + restock batches. Healthy inventory (14.2 sleeves on hand).
A7: PKG-002 | B7: Paper Cup 16oz (Hot Large) | C7: pcs | D7: 2.8 | E7: 300 | F7: 400 | G7: =E7+F7 | H7: 626 | I7: 626 | J7: 300 | K7: =H7-J7 | L7: =G7-H7 | M7: =H7*D7 | N7: =K7*D7 | O7: 🔺 SURPLUS / RESTOCK | P7: 🔵 | Q7: Initial setup 300pcs + deliveries. Sufficient for large hot lattes (12.5 sleeves).
A8: PKG-003 | B8: Paper Cup 8oz (Hot Small) | C8: pcs | D8: 2.4 | E8: 250 | F8: 750 | G8: =E8+F8 | H8: 925 | I8: 925 | J8: 250 | K8: =H8-J8 | L8: =G8-H8 | M8: =H8*D8 | N8: =K8*D8 | O8: 🔺 SURPLUS / RESTOCK | P8: 🔵 | Q8: Initial setup 250pcs + sleeve delivery. Abundant stock for small hot drinks (18.5 sleeves).
A9: Subtotal — 1. CUPS & PACKAGING CONSUMABLES: | E9: =SUMPRODUCT(D6:D8, E6:E8) | F9: =SUMPRODUCT(D6:D8, F6:F8) | G9: =E9+F9 | H9: =SUM(H6:H8) | J9: =SUM(J6:J8) | K9: =SUM(K6:K8) | L9: =SUMPRODUCT(D6:D8, L6:L8) | M9: =SUM(M6:M8) | N9: =SUM(N6:N8)
A10: ☕ 2. COFFEE BEANS & SPECIALTY ROASTS
A11: ING-001 | B11: Concept Blend 1 (Espresso Beans) | C11: pack (1kg) | D11: 980 | E11: 10 | F11: 0 | G11: =E11+F11 | H11: 3 | I11: 3 packs | J11: 5.932 | K11: =H11-J11 | L11: =G11-H11 | M11: =H11*D11 | N11: =K11*D11 | O11: ℹ️ IN-USE / CONSUMED | P11: ⚪ | Q11: Aug 8 Beginning: 10 packs. 7 packs (7kg) ground and consumed. 3 packs remaining on bar. POS tracked 5.93 packs prior to closing.
A12: ING-002 | B12: Australia's Own / Artisanal Roast | C12: pack (1kg) | D12: 204 | E12: 0 | F12: 1 | G12: =E12+F12 | H12: 1 | I12: 1pack (Artisanal brand) | J12: 1 | K12: =H12-J12 | L12: =G12-H12 | M12: =H12*D12 | N12: =K12*D12 | O12: ✅ MATCH | P12: 🟢 | Q12: Aug 13 Delivery: 1.0 pack. 100% Exact match to POS system. Reserve specialty roast sealed.
A13: Subtotal — 2. COFFEE BEANS & SPECIALTY ROASTS: | E13: =SUMPRODUCT(D11:D12, E11:E12) | F13: =SUMPRODUCT(D11:D12, F11:F12) | G13: =E13+F13 | H13: =SUM(H11:H12) | J13: =SUM(J11:J12) | K13: =SUM(K11:K12) | L13: =SUMPRODUCT(D11:D12, L11:L12) | M13: =SUM(M11:M12) | N13: =SUM(N11:N12)
A14: 🍯 3. TORANI FLAVOR SYRUPS & PURÉES
A15: TOR-001 | B15: Torani Irish Cream Syrup 750ml | C15: bottle | D15: 550 | E15: 0 | F15: 1 | G15: =E15+F15 | H15: 1 | I15: 1 bottle | J15: 1 | K15: =H15-J15 | L15: =G15-H15 | M15: =H15*D15 | N15: =K15*D15 | O15: ✅ MATCH | P15: 🟢 | Q15: Aug 24 Delivery: 1.0 bottle. 100% Exact match to POS system. Active bar bottle.
A16: TOR-002 | B16: Torani Salted Caramel Syrup 750ml | C16: bottle | D16: 550 | E16: 0 | F16: 1 | G16: =E16+F16 | H16: 1 | I16: 1bottle | J16: 1 | K16: =H16-J16 | L16: =G16-H16 | M16: =H16*D16 | N16: =K16*D16 | O16: ✅ MATCH | P16: 🟢 | Q16: Aug 24 Delivery: 1.0 bottle. 100% Exact match to POS system. Active bar bottle.
A17: TOR-003 | B17: Torani White Chocolate Syrup 750ml | C17: bottle | D17: 550 | E17: 0 | F17: 1 | G17: =E17+F17 | H17: 1 | I17: 1bottle | J17: 1 | K17: =H17-J17 | L17: =G17-H17 | M17: =H17*D17 | N17: =K17*D17 | O17: ✅ MATCH | P17: 🟢 | Q17: Sept 2 Delivery: 1.0 bottle. 100% Exact match to POS system. Active bar bottle.
A18: TOR-004 | B18: Torani French Vanilla Syrup 750ml | C18: bottle | D18: 550 | E18: 0 | F18: 1 | G18: =E18+F18 | H18: 1 | I18: 1bottle | J18: 1 | K18: =H18-J18 | L18: =G18-H18 | M18: =H18*D18 | N18: =K18*D18 | O18: ✅ MATCH | P18: 🟢 | Q18: Aug 24 Delivery: 1.0 bottle. 100% Exact match to POS system. Active bar bottle.
A19: TOR-005 | B19: Torani Macadamia Nut Syrup 750ml | C19: bottle | D19: 550 | E19: 0 | F19: 1 | G19: =E19+F19 | H19: 1 | I19: 1 bottle | J19: 1 | K19: =H19-J19 | L19: =G19-H19 | M19: =H19*D19 | N19: =K19*D19 | O19: ✅ MATCH | P19: 🟢 | Q19: Aug 24 Delivery: 1.0 bottle. 100% Exact match to POS system. Active bar bottle.
A20: TOR-006 | B20: Torani Hazelnut Syrup 750ml | C20: bottle | D20: 550 | E20: 0 | F20: 1 | G20: =E20+F20 | H20: 1 | I20: 1bottle | J20: 1 | K20: =H20-J20 | L20: =G20-H20 | M20: =H20*D20 | N20: =K20*D20 | O20: ✅ MATCH | P20: 🟢 | Q20: Aug 24 Delivery: 1.0 bottle. 100% Exact match to POS system. Active bar bottle.
A21: TOR-007 | B21: Torani Butterscotch Syrup 750ml | C21: bottle | D21: 550 | E21: 0 | F21: 1 | G21: =E21+F21 | H21: 1 | I21: 1bottle | J21: 1 | K21: =H21-J21 | L21: =G21-H21 | M21: =H21*D21 | N21: =K21*D21 | O21: ✅ MATCH | P21: 🟢 | Q21: Aug 24 Delivery: 1.0 bottle. 100% Exact match to POS system. Active bar bottle.
A22: TOR-008 | B22: Torani Pomegranate Syrup 750ml | C22: bottle | D22: 550 | E22: 0 | F22: 1 | G22: =E22+F22 | H22: 1 | I22: 1bottle | J22: 1 | K22: =H22-J22 | L22: =G22-H22 | M22: =H22*D22 | N22: =K22*D22 | O22: ✅ MATCH | P22: 🟢 | Q22: Aug 24 Delivery: 1.0 bottle. 100% Exact match to POS system. Active bar bottle.
A23: TOR-009 | B23: Torani Lychee Syrup 750ml | C23: bottle | D23: 550 | E23: 0 | F23: 1 | G23: =E23+F23 | H23: 1 | I23: 1bottle | J23: 1 | K23: =H23-J23 | L23: =G23-H23 | M23: =H23*D23 | N23: =K23*D23 | O23: ✅ MATCH | P23: 🟢 | Q23: Aug 24 Delivery: 1.0 bottle. 100% Exact match to POS system. Active bar bottle.
A24: TOR-010 | B24: Torani Caramel Sauce / Syrup (Gallon) | C24: gallon | D24: 950 | E24: 0 | F24: 1 | G24: =E24+F24 | H24: 1 | I24: 1gallon | J24: 1 | K24: =H24-J24 | L24: =G24-H24 | M24: =H24*D24 | N24: =K24*D24 | O24: ✅ MATCH | P24: 🟢 | Q24: Sept 2 Delivery: 1.0 gallon (1.89L). 100% Exact match to POS system. Main caramel jug.
A25: TOR-011 | B25: Torani Mango Purée Blend 1.89L | C25: gallon | D25: 950 | E25: 0 | F25: 1 | G25: =E25+F25 | H25: 1 | I25: 1gallon | J25: 1 | K25: =H25-J25 | L25: =G25-H25 | M25: =H25*D25 | N25: =K25*D25 | O25: ✅ MATCH | P25: 🟢 | Q25: Aug 24 Delivery: 1.0 gallon. 100% Exact match to POS system. Mango puree base for smoothies.
A26: TOR-012 | B26: Torani Strawberry Purée Blend 1.89L | C26: gallon | D26: 950 | E26: 0 | F26: 1 | G26: =E26+F26 | H26: 1 | I26: 1gallon (1L) | J26: 1 | K26: =H26-J26 | L26: =G26-H26 | M26: =H26*D26 | N26: =K26*D26 | O26: ✅ MATCH | P26: 🟢 | Q26: Aug 24 Delivery: 1.0 gallon. 100% Exact match to POS system. Strawberry puree base for frappes.
A27: Subtotal — 3. TORANI FLAVOR SYRUPS & PURÉES: | E27: =SUMPRODUCT(D15:D26, E15:E26) | F27: =SUMPRODUCT(D15:D26, F15:F26) | G27: =E27+F27 | H27: =SUM(H15:H26) | J27: =SUM(J15:J26) | K27: =SUM(K15:K26) | L27: =SUMPRODUCT(D15:D26, L15:L26) | M27: =SUM(M15:M26) | N27: =SUM(N15:N26)
A28: ✨ 4. SHOTT NEW ZEALAND PREMIUM SYRUPS
A29: SHT-001 | B29: SHOTT Pink Guava Syrup 1L | C29: bottle (1L) | D29: 890 | E29: 1 | F29: 0 | G29: =E29+F29 | H29: 0 | I29: empty | J29: -0.08 | K29: =H29-J29 | L29: =G29-H29 | M29: =H29*D29 | N29: =K29*D29 | O29: 🚨 OUT OF STOCK | P29: 🔴 | Q29: Aug 8 Beginning: 1.0 bot. 1.0 bot completely consumed across fruit teas & sodas. 🚨 OUT OF STOCK. Reorder urgent.
A30: SHT-002 | B30: SHOTT Irish Cream Syrup 1L | C30: bottle (1L) | D30: 690 | E30: 1 | F30: 0 | G30: =E30+F30 | H30: 1 | I30: 1bottle (1L) | J30: 1 | K30: =H30-J30 | L30: =G30-H30 | M30: =H30*D30 | N30: =K30*D30 | O30: ✅ MATCH | P30: 🟢 | Q30: Aug 8 Beginning: 1.0 bot. 100% Exact match to POS system. Full 1L bottle on shelf.
A31: SHT-003 | B31: SHOTT Mango Syrup 1L | C31: bottle (1L) | D31: 890 | E31: 1 | F31: 0 | G31: =E31+F31 | H31: 0.21 | I31: 210ml | J31: 0.18 | K31: =H31-J31 | L31: =G31-H31 | M31: =H31*D31 | N31: =K31*D31 | O31: ⚠️ LOW STOCK | P31: 🟡 | Q31: Aug 8 Beginning: 1.0 bot. 790ml consumed. ⚠️ LOW STOCK: 210ml remaining (POS tracked 180ml). Reorder within 3 days.
A32: SHT-004 | B32: SHOTT Macadamia Syrup 1L | C32: bottle (1L) | D32: 690 | E32: 1 | F32: 0 | G32: =E32+F32 | H32: 0.9 | I32: 900ml | J32: -0.21 | K32: =H32-J32 | L32: =G32-H32 | M32: =H32*D32 | N32: =K32*D32 | O32: 🔺 SURPLUS / RESTOCK | P32: 🔵 | Q32: Aug 8 Beginning: 1.0 bot. Fresh replacement bottle opened on bar (900ml remaining). Stock reset required.
A33: SHT-005 | B33: SHOTT Vanilla Syrup 1L | C33: bottle (1L) | D33: 690 | E33: 1 | F33: 0 | G33: =E33+F33 | H33: 1 | I33: 1bottle (1L) | J33: 0.75 | K33: =H33-J33 | L33: =G33-H33 | M33: =H33*D33 | N33: =K33*D33 | O33: 🔺 SURPLUS / RESTOCK | P33: 🔵 | Q33: Aug 8 Beginning: 1.0 bot. Full 1L bottle on hand. POS recorded 0.75L.
A34: SHT-006 | B34: SHOTT Lychee Syrup 1L | C34: bottle (1L) | D34: 690 | E34: 1 | F34: 0 | G34: =E34+F34 | H34: 0.9 | I34: 900ml | J34: 0.76 | K34: =H34-J34 | L34: =G34-H34 | M34: =H34*D34 | N34: =K34*D34 | O34: ✅ MATCH | P34: 🟢 | Q34: Aug 8 Beginning: 1.0 bot. 100ml consumed. 900ml remaining in active rotation.
A35: SHT-007 | B35: SHOTT Pomegranate Syrup 1L | C35: bottle (1L) | D35: 890 | E35: 1 | F35: 0 | G35: =E35+F35 | H35: 0.25 | I35: 250ml | J35: 0.25 | K35: =H35-J35 | L35: =G35-H35 | M35: =H35*D35 | N35: =K35*D35 | O35: ⚠️ LOW STOCK | P35: 🟡 | Q35: Aug 8 Beginning: 1.0 bot. 750ml consumed. ⚠️ LOW STOCK: 250ml remaining. 100% PERFECT MATCH to POS stock (0.25L)!
A36: Subtotal — 4. SHOTT NEW ZEALAND PREMIUM SYRUPS: | E36: =SUMPRODUCT(D29:D35, E29:E35) | F36: =SUMPRODUCT(D29:D35, F29:F35) | G36: =E36+F36 | H36: =SUM(H29:H35) | J36: =SUM(J29:J35) | K36: =SUM(K29:K35) | L36: =SUMPRODUCT(D29:D35, L29:L35) | M36: =SUM(M29:M35) | N36: =SUM(N29:N35)
A37: 🧈 5. CONDIMENTS, SPREADS & MIXES
A38: MIX-001 | B38: Biscoff Sauce Mix (In-House Prep) | C38: grams | D38: 0.86 | E38: 0 | F38: 250 | G38: =E38+F38 | H38: 213 | I38: 213g | J38: 250 | K38: =H38-J38 | L38: =G38-H38 | M38: =H38*D38 | N38: =K38*D38 | O38: ℹ️ IN-USE / CONSUMED | P38: ⚪ | Q38: In-house prepared sauce drizzle bottle. 213g on bar station.
A39: MIX-002 | B39: Lotus Biscoff Spread Smooth 400g | C39: grams | D39: 0.86 | E39: 0 | F39: 400 | G39: =E39+F39 | H39: 201 | I39: 201g | J39: 250 | K39: =H39-J39 | L39: =G39-H39 | M39: =H39*D39 | N39: =K39*D39 | O39: ℹ️ IN-USE / CONSUMED | P39: ⚪ | Q39: Aug 13 Delivery: 1 pack (400g). 199g consumed in Biscoff lattes. ~0.5 jar (201g) left.
A40: MIX-003 | B40: Lotus Biscoff Biscuits (Garnish) | C40: pcs | D40: 6 | E40: 0 | F40: 32 | G40: =E40+F40 | H40: 13 | I40: 13pcs biscuit | J40: 32 | K40: =H40-J40 | L40: =G40-H40 | M40: =H40*D40 | N40: =K40*D40 | O40: ℹ️ IN-USE / CONSUMED | P40: ⚪ | Q40: Aug 13 Delivery: 1 pack (approx 32 pcs). 19 pcs used for drink toppings. 13 pcs left.
A41: MIX-004 | B41: Sugar Syrup (Hi-Fructose 500ml) | C41: bottles | D41: 94 | E41: 1 | F41: 10 | G41: =E41+F41 | H41: 3 | I41: 3 bottle | J41: 10 | K41: =H41-J41 | L41: =G41-H41 | M41: =H41*D41 | N41: =K41*D41 | O41: ℹ️ IN-USE / CONSUMED | P41: ⚪ | Q41: Aug 8 Beginning: 1 bot + Aug 13 Delivery: 10 bot = 11.0 Total. 8 bottles consumed across beverages! 3 remaining.
A42: MIX-005 | B42: Caramel Mix (Bakersfield Caramel Fudge) | C42: grams | D42: 0.415 | E42: 0 | F42: 1000 | G42: =E42+F42 | H42: 749.6 | I42: 268g + 481.6g | J42: 1000 | K42: =H42-J42 | L42: =G42-H42 | M42: =H42*D42 | N42: =K42*D42 | O42: ℹ️ IN-USE / CONSUMED | P42: ⚪ | Q42: Aug 13 Delivery: 1kg (1,000g). 749.6g total on hand (268g dispenser + 481.6g tub). 250.4g used.
A43: MIX-006 | B43: Doreen Condensed Milk 390g | C43: cans | D43: 44 | E43: 24 | F43: 0 | G43: =E43+F43 | H43: 12.53 | I43: 205g + 12cans | J43: 18.74 | K43: =H43-J43 | L43: =G43-H43 | M43: =H43*D43 | N43: =K43*D43 | O43: ℹ️ IN-USE / CONSUMED | P43: ⚪ | Q43: Aug 8 Beginning: 24.0 cans (full case). 11.47 cans consumed in Spanish Lattes. 12 sealed cans + 205g open can.
A44: Subtotal — 5. CONDIMENTS, SPREADS & MIXES: | E44: =SUMPRODUCT(D38:D43, E38:E43) | F44: =SUMPRODUCT(D38:D43, F38:F43) | G44: =E44+F44 | H44: =SUM(H38:H43) | J44: =SUM(J38:J43) | K44: =SUM(K38:K43) | L44: =SUMPRODUCT(D38:D43, L38:L43) | M44: =SUM(M38:M43) | N44: =SUM(N38:N43)
A45: 🍃 6. POWDERS & BREWING TEA LEAVES
A46: POW-001 | B46: Oreo Crushed Cookie Crumbs 454g | C46: grams | D46: 0.385 | E46: 0 | F46: 454 | G46: =E46+F46 | H46: 296 | I46: 296g | J46: 454 | K46: =H46-J46 | L46: =G46-H46 | M46: =H46*D46 | N46: =K46*D46 | O46: ℹ️ IN-USE / CONSUMED | P46: ⚪ | Q46: Aug 13 Delivery: 1 pack (454g). 158g used for Dirty Oreo & frappes. 296g on station.
A47: POW-002 | B47: Easy Cookies & Cream Powder 1kg | C47: grams | D47: 0.305 | E47: 0 | F47: 1000 | G47: =E47+F47 | H47: 897 | I47: 615g + 282g | J47: 1000 | K47: =H47-J47 | L47: =G47-H47 | M47: =H47*D47 | N47: =K47*D47 | O47: ℹ️ IN-USE / CONSUMED | P47: ⚪ | Q47: Aug 13 Delivery: 1 pack (1,000g). 103g used. 897g total across container (282g) + pouch (615g).
A48: POW-003 | B48: Matcha Powder (Pure / Culinary) | C48: grams | D48: 1.2 | E48: 0 | F48: 300 | G48: =E48+F48 | H48: 101 | I48: 101g | J48: 100 | K48: =H48-J48 | L48: =G48-H48 | M48: =H48*D48 | N48: =K48*D48 | O48: ✅ MATCH | P48: 🟢 | Q48: Aug 13 Delivery: 3 packs (100g each = 300g). 101g currently in active bar canister.
A49: POW-004 | B49: Black Tea Leaves (Possmei Assam) | C49: grams | D49: 0.733 | E49: 0 | F49: 600 | G49: =E49+F49 | H49: 698 | I49: 401g + 297g | J49: 600 | K49: =H49-J49 | L49: =G49-H49 | M49: =H49*D49 | N49: =K49*D49 | O49: 🔺 SURPLUS / RESTOCK | P49: 🔵 | Q49: Aug 13 Delivery: 1 pack (600g). 698g total on hand across brewing jar (297g) + pack (401g).
A50: POW-005 | B50: Jasmine Green Tea Leaves (Possmei) | C50: grams | D50: 1.28 | E50: 0 | F50: 600 | G50: =E50+F50 | H50: 597 | I50: 302g + 295g | J50: 600 | K50: =H50-J50 | L50: =G50-H50 | M50: =H50*D50 | N50: =K50*D50 | O50: ✅ MATCH | P50: 🟢 | Q50: Aug 13 Delivery: 1 pack (600g). 597g total (295g station + 302g pack). Virtually exact match (99.5%)!
A51: POW-006 | B51: Easy Dark Choco Powder Base 1kg | C51: grams | D51: 0.396 | E51: 1000 | F51: 1000 | G51: =E51+F51 | H51: 1612 | I51: 326g + 286g + 1pack (1kg) | J51: 1000 | K51: =H51-J51 | L51: =G51-H51 | M51: =H51*D51 | N51: =K51*D51 | O51: 🔺 SURPLUS / RESTOCK | P51: 🔵 | Q51: Aug 8 Beginning: 1,000g + Aug 13 Delivery: 1,000g = 2,000g Total. 388g used. 1 full sealed pack + 612g active.
A52: POW-007 | B52: Artisanal Salted Cream Cheese Powder | C52: grams | D52: 0.4 | E52: 0 | F52: 1000 | G52: =E52+F52 | H52: 448 | I52: 448g | J52: 500 | K52: =H52-J52 | L52: =G52-H52 | M52: =H52*D52 | N52: =K52*D52 | O52: ℹ️ IN-USE / CONSUMED | P52: ⚪ | Q52: Aug 13 Delivery: 2 packs (~1,000g). 448g on bar for cheese foam & seasalt cold foam prep.
A53: Subtotal — 6. POWDERS & BREWING TEA LEAVES: | E53: =SUMPRODUCT(D46:D52, E46:E52) | F53: =SUMPRODUCT(D46:D52, F46:F52) | G53: =E53+F53 | H53: =SUM(H46:H52) | J53: =SUM(J46:J52) | K53: =SUM(K46:K52) | L53: =SUMPRODUCT(D46:D52, L46:L52) | M53: =SUM(M46:M52) | N53: =SUM(N46:N52)
A54: 🍵 7. DILMAH SPECIALTY TEA PACKS
A55: DLM-001 | B55: Dilmah Pure Chamomile Flowers Tea | C55: sachets | D55: 45 | E55: 0 | F55: 100 | G55: =E55+F55 | H55: 100 | I55: 100pcs | J55: 100 | K55: =H55-J55 | L55: =G55-H55 | M55: =H55*D55 | N55: =K55*D55 | O55: ✅ MATCH | P55: 🟢 | Q55: Aug 24 Delivery: 100 sachets (1 box). 100% PERFECT MATCH to POS stock (100 sachets). Zero shrinkage.
A56: DLM-002 | B56: Dilmah Earl Grey Tea | C56: sachets | D56: 45 | E56: 0 | F56: 100 | G56: =E56+F56 | H56: 93 | I56: 93pcs | J56: 91 | K56: =H56-J56 | L56: =G56-H56 | M56: =H56*D56 | N56: =K56*D56 | O56: ✅ MATCH | P56: 🟢 | Q56: Aug 24 Delivery: 100 sachets (1 box). 7 sold. 93 sachets counted. POS recorded 91 sachets (minor +2 variance).
A57: DLM-003 | B57: Dilmah Pure Peppermint Leaves Tea | C57: sachets | D57: 45 | E57: 0 | F57: 100 | G57: =E57+F57 | H57: 98 | I57: 98pcs | J57: 98 | K57: =H57-J57 | L57: =G57-H57 | M57: =H57*D57 | N57: =K57*D57 | O57: ✅ MATCH | P57: 🟢 | Q57: Aug 24 Delivery: 100 sachets (1 box). 2 sold. 100% PERFECT MATCH to POS stock (98 sachets).
A58: DLM-004 | B58: Dilmah Gourmet Pure Green Tea | C58: sachets | D58: 45 | E58: 0 | F58: 100 | G58: =E58+F58 | H58: 100 | I58: 100pcs | J58: 100 | K58: =H58-J58 | L58: =G58-H58 | M58: =H58*D58 | N58: =K58*D58 | O58: ✅ MATCH | P58: 🟢 | Q58: Aug 24 Delivery: 100 sachets (1 box). 100% PERFECT MATCH to POS stock (100 sachets). Zero shrinkage.
A59: DLM-005 | B59: Dilmah Traditional Oolong Tea | C59: sachets | D59: 45 | E59: 0 | F59: 100 | G59: =E59+F59 | H59: 100 | I59: 100pcs | J59: 100 | K59: =H59-J59 | L59: =G59-H59 | M59: =H59*D59 | N59: =K59*D59 | O59: ✅ MATCH | P59: 🟢 | Q59: Aug 24 Delivery: 100 sachets (1 box). 100% PERFECT MATCH to POS stock (100 sachets). Zero shrinkage.
A60: DLM-006 | B60: Dilmah Green Tea with Jasmine | C60: sachets | D60: 45 | E60: 0 | F60: 100 | G60: =E60+F60 | H60: 100 | I60: 100pcs | J60: 100 | K60: =H60-J60 | L60: =G60-H60 | M60: =H60*D60 | N60: =K60*D60 | O60: ✅ MATCH | P60: 🟢 | Q60: Aug 24 Delivery: 100 sachets (1 box). 100% PERFECT MATCH to POS stock (100 sachets). Zero shrinkage.
A61: Subtotal — 7. DILMAH SPECIALTY TEA PACKS: | E61: =SUMPRODUCT(D55:D60, E55:E60) | F61: =SUMPRODUCT(D55:D60, F55:F60) | G61: =E61+F61 | H61: =SUM(H55:H60) | J61: =SUM(J55:J60) | K61: =SUM(K55:K60) | L61: =SUMPRODUCT(D55:D60, L55:L60) | M61: =SUM(M55:M60) | N61: =SUM(N55:N60)
A62: 🥨 8. GRAB-AND-GO RETAIL SNACKS
A63: SNK-001 | B63: Pringles Cheddar Cheese 158g | C63: cans | D63: 98 | E63: 0 | F63: 3 | G63: =E63+F63 | H63: 3 | I63: 3pcs | J63: 10 | K63: =H63-J63 | L63: =G63-H63 | M63: =H63*D63 | N63: =K63*D63 | O63: ⚠️ LOW STOCK | P63: 🟡 | Q63: Aug 24 Delivery: 3 cans (initial batch 10 cans). ⚠️ LOW STOCK: 3 cans remaining. Reorder 1 case.
A64: SNK-002 | B64: Pringles Original 158g | C64: cans | D64: 98 | E64: 0 | F64: 3 | G64: =E64+F64 | H64: 3 | I64: 3pcs | J64: 10 | K64: =H64-J64 | L64: =G64-H64 | M64: =H64*D64 | N64: =K64*D64 | O64: ⚠️ LOW STOCK | P64: 🟡 | Q64: Aug 24 Delivery: 3 cans (initial batch 10 cans). ⚠️ LOW STOCK: 3 cans remaining. Reorder 1 case.
A65: SNK-003 | B65: Pringles Sour Cream & Onion 158g | C65: cans | D65: 98 | E65: 0 | F65: 3 | G65: =E65+F65 | H65: 0 | I65: empty | J65: 10 | K65: =H65-J65 | L65: =G65-H65 | M65: =H65*D65 | N65: =K65*D65 | O65: 🚨 OUT OF STOCK | P65: 🔴 | Q65: Aug 24 Delivery: 3 cans (initial batch 10 cans). 🚨 OUT OF STOCK: Completely sold out. Reorder 1 case urgent.
A66: SNK-004 | B66: Cheetos Cheddar Jalapeño 226.8g | C66: packs | D66: 98 | E66: 0 | F66: 3 | G66: =E66+F66 | H66: 3 | I66: 3pcs | J66: 8 | K66: =H66-J66 | L66: =G66-H66 | M66: =H66*D66 | N66: =K66*D66 | O66: ⚠️ LOW STOCK | P66: 🟡 | Q66: Aug 24 Delivery: 3 packs. ⚠️ LOW STOCK: 3 packs remaining. Reorder 1 batch (8 packs).
A67: SNK-005 | B67: Butter Lover Popcorn Bags | C67: bags | D67: 85 | E67: 0 | F67: 32 | G67: =E67+F67 | H67: 32 | I67: 32packs | J67: 12 | K67: =H67-J67 | L67: =G67-H67 | M67: =H67*D67 | N67: =K67*D67 | O67: 🔺 SURPLUS / RESTOCK | P67: 🔵 | Q67: Aug 24 Delivery: 32 bags (1 box). Plentiful inventory: 32 bags on shelf/backroom. Full stock.
A68: Subtotal — 8. GRAB-AND-GO RETAIL SNACKS: | E68: =SUMPRODUCT(D63:D67, E63:E67) | F68: =SUMPRODUCT(D63:D67, F63:F67) | G68: =E68+F68 | H68: =SUM(H63:H67) | J68: =SUM(J63:J67) | K68: =SUM(K63:K67) | L68: =SUMPRODUCT(D63:D67, L63:L67) | M68: =SUM(M63:M67) | N68: =SUM(N63:N67)
A69: 🥤 9. RETAIL DRINKS, WATER & BEERS
A70: BEV-001 | B70: Coca-Cola Zero Sugar 320ml Can | C70: cans | D70: 35 | E70: 0 | F70: 24 | G70: =E70+F70 | H70: 20 | I70: 20pcs | J70: 17 | K70: =H70-J70 | L70: =G70-H70 | M70: =H70*D70 | N70: =K70*D70 | O70: ✅ MATCH | P70: 🟢 | Q70: Aug 24 Delivery: 24 cans (1 case). 4 sold (20 remaining). POS recorded 7 sold (minor +3 delta).
A71: BEV-002 | B71: Coca-Cola Regular 320ml Can | C71: cans | D71: 35 | E71: 0 | F71: 24 | G71: =E71+F71 | H71: 24 | I71: 24pcs | J71: 23 | K71: =H71-J71 | L71: =G71-H71 | M71: =H71*D71 | N71: =K71*D71 | O71: ✅ MATCH | P71: 🟢 | Q71: Aug 24 Delivery: 24 cans (1 case). 24 cans full case on hand. Healthy inventory.
A72: BEV-003 | B72: Sprite Soda 320ml Can | C72: cans | D72: 35 | E72: 0 | F72: 24 | G72: =E72+F72 | H72: 21 | I72: 21pcs | J72: 18 | K72: =H72-J72 | L72: =G72-H72 | M72: =H72*D72 | N72: =K72*D72 | O72: ✅ MATCH | P72: 🟢 | Q72: Aug 24 Delivery: 24 cans (1 case). 3 sold (21 remaining in chiller). POS recorded 6 sold.
A73: BEV-004 | B73: Sprite 1.5L Bottle (Bar Mixer) | C73: bottles | D73: 69.5 | E73: 4 | F73: 6 | G73: =E73+F73 | H73: 1.5 | I73: 1bottle and half bottle | J73: 2 | K73: =H73-J73 | L73: =G73-H73 | M73: =H73*D73 | N73: =K73*D73 | O73: ℹ️ IN-USE / CONSUMED | P73: ⚪ | Q73: Aug 8 Beginning: 4 bot + Aug 24 Delivery: 6 bot = 10.0 Total. 8.5 bottles consumed for Fruit Sodas! 1.5 bottles left.
A74: BEV-005 | B74: Nature Spring Mineral Water 500ml | C74: bottles | D74: 12 | E74: 0 | F74: 35 | G74: =E74+F74 | H74: 0 | I74: empty | J74: 0 | K74: =H74-J74 | L74: =G74-H74 | M74: =H74*D74 | N74: =K74*D74 | O74: 🚨 OUT OF STOCK | P74: 🔴 | Q74: Aug 24 Delivery: 35 bottles. 🚨 CRITICAL OUT OF STOCK: All sold (POS logged 54 sales). Urgent reorder needed!
A75: BEV-006 | B75: Nature Spring Mineral Water 1L | C75: bottles | D75: 18 | E75: 0 | F75: 20 | G75: =E75+F75 | H75: 15 | I75: 15pcs | J75: 15 | K75: =H75-J75 | L75: =G75-H75 | M75: =H75*D75 | N75: =K75*D75 | O75: ✅ MATCH | P75: 🟢 | Q75: Initial delivery: 20 bottles. 5 customer sales in POS. 20 - 5 = EXACTLY 15 BOTTLES! Zero shrinkage.
A76: BEV-007 | B76: Red Horse Stallion Beer 330ml | C76: bottles | D76: 55 | E76: 0 | F76: 48 | G76: =E76+F76 | H76: 39 | I76: 39bottle | J76: 15 | K76: =H76-J76 | L76: =G76-H76 | M76: =H76*D76 | N76: =K76*D76 | O76: 🔺 SURPLUS / RESTOCK | P76: 🔵 | Q76: Aug 24 Delivery: 48 bottles (2 cases). 9 sold. 39 bottles on hand in chiller. Ample stock.
A77: BEV-008 | B77: San Miguel Pale Pilsen 320ml | C77: bottles | D77: 52 | E77: 0 | F77: 48 | G77: =E77+F77 | H77: 50 | I77: 50bottle | J77: 12 | K77: =H77-J77 | L77: =G77-H77 | M77: =H77*D77 | N77: =K77*D77 | O77: 🔺 SURPLUS / RESTOCK | P77: 🔵 | Q77: Aug 24 Delivery: 48 bottles (2 cases) + buffer. 50 bottles on hand. Ample stock.
A78: BEV-009 | B78: San Mig Light - Apple 330ml | C78: bottles | D78: 48 | E78: 0 | F78: 24 | G78: =E78+F78 | H78: 22 | I78: 22bottle | J78: 12 | K78: =H78-J78 | L78: =G78-H78 | M78: =H78*D78 | N78: =K78*D78 | O78: 🔺 SURPLUS / RESTOCK | P78: 🔵 | Q78: Aug 24 Delivery: 24 bottles (1 case). 2 sold. 22 bottles in chiller. Healthy stock.
A79: BEV-010 | B79: Evian Natural Spring Water 500ml | C79: bottles | D79: 95 | E79: 0 | F79: 6 | G79: =E79+F79 | H79: 6 | I79: 6pcs | J79: 12 | K79: =H79-J79 | L79: =G79-H79 | M79: =H79*D79 | N79: =K79*D79 | O79: ⚠️ LOW STOCK | P79: 🟡 | Q79: Aug 24 Delivery: 6 bottles. 6 bottles remaining in chiller. Monitor chiller level.
A80: BEV-011 | B80: Perrier Sparkling Mineral Water 330ml | C80: bottles | D80: 110 | E80: 0 | F80: 4 | G80: =E80+F80 | H80: 4 | I80: 4 bottle | J80: 12 | K80: =H80-J80 | L80: =G80-H80 | M80: =H80*D80 | N80: =K80*D80 | O80: ⚠️ LOW STOCK | P80: 🟡 | Q80: Aug 24 Delivery: 4 bottles. ⚠️ LOW STOCK: 4 bottles remaining. Reorder 1 pack.
A81: Subtotal — 9. RETAIL DRINKS, WATER & BEERS: | E81: =SUMPRODUCT(D70:D80, E70:E80) | F81: =SUMPRODUCT(D70:D80, F70:F80) | G81: =E81+F81 | H81: =SUM(H70:H80) | J81: =SUM(J70:J80) | K81: =SUM(K70:K80) | L81: =SUMPRODUCT(D70:D80, L70:L80) | M81: =SUM(M70:M80) | N81: =SUM(N70:N80)
A82: 🏆 GRAND TOTAL (ALL 59 AUDITED ITEMS): | E82: =SUM('📊 Executive Summary'!C10:C18) | F82: =SUM('📊 Executive Summary'!D10:D18) | G82: =SUM('📊 Executive Summary'!E10:E18) | M82: =SUM('📊 Executive Summary'!F10:F18)

Sheet 🚨 Reorder & Action List
A1: ESPRESSO YOURSELF & TEA HOUSE — PRIORITY RESTOCKING & PURCHASING LIST
A2: Items Requiring Immediate Purchasing or Supplier Delivery based on Physical Inventory Audit
A4: Priority | B4: Item Description & SKU | C4: Current Count | D4: Target Par Level | E4: Suggested Order Qty | F4: Est. Unit Cost | G4: Est. Reorder Cost (₱)
A5: 🚨 CRITICAL | B5: Nature Spring Mineral Water 500ml | C5: 0 (EMPTY) | D5: 50 bottles | E5: 2 Cases (48 bottles) | F5: 12 | G5: 576
A6: 🚨 CRITICAL | B6: Pringles Sour Cream & Onion 158g | C6: 0 (EMPTY) | D6: 10 cans | E6: 1 Case (12 cans) | F6: 98 | G6: 1176
A7: 🚨 CRITICAL | B7: SHOTT Pink Guava Syrup 1L | C7: 0 (EMPTY) | D7: 2 bottles | E7: 2 Bottles (1L) | F7: 890 | G7: 1780
A8: ⚠️ HIGH | B8: Pringles Cheddar Cheese 158g | C8: 3 cans | D8: 10 cans | E8: 1 Case (12 cans) | F8: 98 | G8: 1176
A9: ⚠️ HIGH | B9: Pringles Original 158g | C9: 3 cans | D9: 10 cans | E9: 1 Case (12 cans) | F9: 98 | G9: 1176
A10: ⚠️ HIGH | B10: Cheetos Cheddar Jalapeño 226.8g | C10: 3 packs | D10: 8 packs | E10: 1 Box (8 packs) | F10: 98 | G10: 784
A11: ⚠️ HIGH | B11: SHOTT Mango Syrup 1L | C11: 210ml | D11: 1 bottle | E11: 1 Bottle (1L) | F11: 890 | G11: 890
A12: ⚠️ HIGH | B12: SHOTT Pomegranate Syrup 1L | C12: 250ml | D12: 1 bottle | E12: 1 Bottle (1L) | F12: 890 | G12: 890
A13: 🟡 MEDIUM | B13: Perrier Sparkling Mineral Water 330ml | C13: 4 bottles | D13: 12 bottles | E13: 1 Pack (12 bottles) | F13: 110 | G13: 1320
A14: 🟡 MEDIUM | B14: Sugar Syrup (Hi-Fructose 500ml) | C14: 3 bottles | D14: 10 bottles | E14: 1 Box (6 bottles) | F14: 94 | G14: 564
A15: 🟡 MEDIUM | B15: Evian Natural Spring Water 500ml | C15: 6 bottles | D15: 12 bottles | E15: 1 Pack (6 bottles) | F15: 95 | G15: 570
A16: ESTIMATED TOTAL URGENT PROCUREMENT BUDGET: | G16: =SUM(G5:G15)
